<?xml version="1.0"?>
<Results version="1.0">
<ReportNode type="testrun">
<ReportNode type="Action">
<ReportNode type="User">
<Data>
    <Name>Start</Name>
    <Description>Iteration1 started</Description>
    <StartTime>2015-11-04 11:40:01</StartTime>
    <Result>Done</Result>
    <Extension>
      <IconKey>e8853b6f99bf44b9a199e7ac21503422</IconKey>
      <IsPlainTextNodeName>True</IsPlainTextNodeName>
      <IsPlainTextStepInfo>True</IsPlainTextStepInfo>
    </Extension>
  </Data>
</ReportNode>
<ReportNode type="User">
<Data>
    <Name>Start Component</Name>
    <Description>Invoking Business component: Login</Description>
    <StartTime>2015-11-04 11:40:01</StartTime>
    <Result>Done</Result>
    <Extension>
      <IconKey>e8853b6f99bf44b9a199e7ac21503422</IconKey>
      <IsPlainTextNodeName>True</IsPlainTextNodeName>
      <IsPlainTextStepInfo>True</IsPlainTextStepInfo>
    </Extension>
  </Data>
</ReportNode>
<ReportNode type="Step">
<Data>
    <Name>SystemUtil.Run "iexplore",3</Name>
    <Description>SystemUtil.Run "iexplore",3</Description>
    <StartTime>2015-11-04 11:40:02</StartTime>
    <Result>Passed</Result>
    <Extension>
      <IconKey>d3be6ab277914e2e96dfe829e0a3f01f</IconKey>
    </Extension>
  </Data>
</ReportNode>
<ReportNode type="Context">
<ReportNode type="Step">
<Data>
    <Name>"Login"- Smart Identification</Name>
    <Description>&lt;P&gt;&lt;span class="text"&gt;The smart identification mechanism was invoked.&lt;/span&gt;&lt;/P&gt;&lt;P&gt;&lt;SPAN class=text&gt;Reason: object not unique (2 objects found)&lt;/SPAN&gt;&lt;/P&gt;           &lt;SPAN class=text&gt;&lt;b&gt;Original description:&lt;/b&gt;&lt;/SPAN&gt;&lt;br&gt;micclass=Browser&lt;br&gt;&lt;P&gt;&lt;FONT face=Verdana size=2&gt;&lt;SPAN class=text&gt;&lt;B&gt;Smart Identification Alternative Description: &lt;/B&gt;&lt;/SPAN&gt;&lt;/FONT&gt;&lt;/P&gt;&lt;FONT face=Verdana size=2&gt;&lt;u&gt;Base filter properties (2 objects found)&amp;nbsp;&lt;/FONT&gt;&lt;/u&gt;&lt;br&gt;
micclass=Browser&lt;br&gt;&lt;br&gt;&lt;FONT face=Verdana size=2&gt;&lt;u&gt;Optional filter properties&lt;/FONT&gt;&lt;/u&gt;&lt;br&gt;
name=Oracle Applications Home Page&lt;SPAN class=Failed&gt; (Skipped)&lt;/SPAN&gt;&lt;br&gt;title=Oracle Applications Home Page&lt;SPAN class=Failed&gt; (Skipped)&lt;/SPAN&gt;&lt;br&gt;openurl=http://www.bing.com&lt;SPAN class=passed&gt; (Used&lt;/SPAN&gt;, 1 matches)&lt;/SPAN&gt;&lt;br&gt;opentitle=&lt;SPAN class=warning&gt; (Ignored)&lt;FONT color=#000000&gt;&lt;/FONT&gt;&lt;/SPAN&gt;&lt;br&gt;hasstatusbar=-1&lt;SPAN class=warning&gt; (Ignored)&lt;FONT color=#000000&gt;&lt;/FONT&gt;&lt;/SPAN&gt;&lt;br&gt;hasmenubar=-1&lt;SPAN class=warning&gt; (Ignored)&lt;FONT color=#000000&gt;&lt;/FONT&gt;&lt;/SPAN&gt;&lt;br&gt;hastoolbar=-1&lt;SPAN class=warning&gt; (Ignored)&lt;FONT color=#000000&gt;&lt;/FONT&gt;&lt;/SPAN&gt;&lt;br&gt;openedbytestingtool=0&lt;SPAN class=warning&gt; (Ignored)&lt;FONT color=#000000&gt;&lt;/FONT&gt;&lt;/SPAN&gt;&lt;br&gt;number of tabs=1&lt;SPAN class=warning&gt; (Ignored)&lt;FONT color=#000000&gt;&lt;/FONT&gt;&lt;/SPAN&gt;&lt;br&gt;</Description>
    <StartTime>2015-11-04 11:40:04</StartTime>
    <Result>Done</Result>
    <Extension>
      <TestObject>
        <Repository>C:\Users\sravanthi\Documents\GitHub\RACK-EBS-Master-Data\Business Components\Libraries\Object Repository\Oracle_EBS.tsr</Repository>
        <Path>
          <Object>
            <Type>Browser</Type>
            <Name><![CDATA[Login]]></Name>
          </Object>
        </Path>
        <OperationData><![CDATA[<P><span class="text">The smart identification mechanism was invoked.</span></P><P><SPAN class=text>Reason: object not unique (2 objects found)</SPAN></P>           <SPAN class=text><b>Original description:</b></SPAN><br>micclass=Browser<br><P><FONT face=Verdana size=2><SPAN class=text><B>Smart Identification Alternative Description: </B></SPAN></FONT></P><FONT face=Verdana size=2><u>Base filter properties (2 objects found)&nbsp;</FONT></u><br>
micclass=Browser<br><br><FONT face=Verdana size=2><u>Optional filter properties</FONT></u><br>
name=Oracle Applications Home Page<SPAN class=Failed> (Skipped)</SPAN><br>title=Oracle Applications Home Page<SPAN class=Failed> (Skipped)</SPAN><br>openurl=http://www.bing.com<SPAN class=passed> (Used</SPAN>, 1 matches)</SPAN><br>opentitle=<SPAN class=warning> (Ignored)<FONT color=#000000></FONT></SPAN><br>hasstatusbar=-1<SPAN class=warning> (Ignored)<FONT color=#000000></FONT></SPAN><br>hasmenubar=-1<SPAN class=warning> (Ignored)<FONT color=#000000></FONT></SPAN><br>hastoolbar=-1<SPAN class=warning> (Ignored)<FONT color=#000000></FONT></SPAN><br>openedbytestingtool=0<SPAN class=warning> (Ignored)<FONT color=#000000></FONT></SPAN><br>number of tabs=1<SPAN class=warning> (Ignored)<FONT color=#000000></FONT></SPAN><br>]]></OperationData>
      </TestObject>
      <IconKey>da8fe7478c1f409db486703ef05c28ae</IconKey>
    </Extension>
  </Data>
</ReportNode>
<ReportNode type="Step">
<Data>
    <Name>"Login"- Smart Identification</Name>
    <Description>&lt;P&gt;&lt;span class="text"&gt;The smart identification mechanism was invoked.&lt;/span&gt;&lt;/P&gt;&lt;P&gt;&lt;SPAN class=text&gt;Reason: object not unique (2 objects found)&lt;/SPAN&gt;&lt;/P&gt;           &lt;SPAN class=text&gt;&lt;b&gt;Original description:&lt;/b&gt;&lt;/SPAN&gt;&lt;br&gt;micclass=Browser&lt;br&gt;&lt;P&gt;&lt;FONT face=Verdana size=2&gt;&lt;SPAN class=text&gt;&lt;B&gt;Smart Identification Alternative Description: &lt;/B&gt;&lt;/SPAN&gt;&lt;/FONT&gt;&lt;/P&gt;&lt;FONT face=Verdana size=2&gt;&lt;u&gt;Base filter properties (2 objects found)&amp;nbsp;&lt;/FONT&gt;&lt;/u&gt;&lt;br&gt;
micclass=Browser&lt;br&gt;&lt;br&gt;&lt;FONT face=Verdana size=2&gt;&lt;u&gt;Optional filter properties&lt;/FONT&gt;&lt;/u&gt;&lt;br&gt;
name=Oracle Applications Home Page&lt;SPAN class=Failed&gt; (Skipped)&lt;/SPAN&gt;&lt;br&gt;title=Oracle Applications Home Page&lt;SPAN class=Failed&gt; (Skipped)&lt;/SPAN&gt;&lt;br&gt;openurl=http://www.bing.com&lt;SPAN class=passed&gt; (Used&lt;/SPAN&gt;, 1 matches)&lt;/SPAN&gt;&lt;br&gt;opentitle=&lt;SPAN class=warning&gt; (Ignored)&lt;FONT color=#000000&gt;&lt;/FONT&gt;&lt;/SPAN&gt;&lt;br&gt;hasstatusbar=-1&lt;SPAN class=warning&gt; (Ignored)&lt;FONT color=#000000&gt;&lt;/FONT&gt;&lt;/SPAN&gt;&lt;br&gt;hasmenubar=-1&lt;SPAN class=warning&gt; (Ignored)&lt;FONT color=#000000&gt;&lt;/FONT&gt;&lt;/SPAN&gt;&lt;br&gt;hastoolbar=-1&lt;SPAN class=warning&gt; (Ignored)&lt;FONT color=#000000&gt;&lt;/FONT&gt;&lt;/SPAN&gt;&lt;br&gt;openedbytestingtool=0&lt;SPAN class=warning&gt; (Ignored)&lt;FONT color=#000000&gt;&lt;/FONT&gt;&lt;/SPAN&gt;&lt;br&gt;number of tabs=1&lt;SPAN class=warning&gt; (Ignored)&lt;FONT color=#000000&gt;&lt;/FONT&gt;&lt;/SPAN&gt;&lt;br&gt;</Description>
    <StartTime>2015-11-04 11:40:05</StartTime>
    <Result>Done</Result>
    <Extension>
      <TestObject>
        <Repository>C:\Users\sravanthi\Documents\GitHub\RACK-EBS-Master-Data\Business Components\Libraries\Object Repository\Oracle_EBS.tsr</Repository>
        <Path>
          <Object>
            <Type>Browser</Type>
            <Name><![CDATA[Login]]></Name>
          </Object>
        </Path>
        <OperationData><![CDATA[<P><span class="text">The smart identification mechanism was invoked.</span></P><P><SPAN class=text>Reason: object not unique (2 objects found)</SPAN></P>           <SPAN class=text><b>Original description:</b></SPAN><br>micclass=Browser<br><P><FONT face=Verdana size=2><SPAN class=text><B>Smart Identification Alternative Description: </B></SPAN></FONT></P><FONT face=Verdana size=2><u>Base filter properties (2 objects found)&nbsp;</FONT></u><br>
micclass=Browser<br><br><FONT face=Verdana size=2><u>Optional filter properties</FONT></u><br>
name=Oracle Applications Home Page<SPAN class=Failed> (Skipped)</SPAN><br>title=Oracle Applications Home Page<SPAN class=Failed> (Skipped)</SPAN><br>openurl=http://www.bing.com<SPAN class=passed> (Used</SPAN>, 1 matches)</SPAN><br>opentitle=<SPAN class=warning> (Ignored)<FONT color=#000000></FONT></SPAN><br>hasstatusbar=-1<SPAN class=warning> (Ignored)<FONT color=#000000></FONT></SPAN><br>hasmenubar=-1<SPAN class=warning> (Ignored)<FONT color=#000000></FONT></SPAN><br>hastoolbar=-1<SPAN class=warning> (Ignored)<FONT color=#000000></FONT></SPAN><br>openedbytestingtool=0<SPAN class=warning> (Ignored)<FONT color=#000000></FONT></SPAN><br>number of tabs=1<SPAN class=warning> (Ignored)<FONT color=#000000></FONT></SPAN><br>]]></OperationData>
      </TestObject>
      <IconKey>da8fe7478c1f409db486703ef05c28ae</IconKey>
    </Extension>
  </Data>
</ReportNode>
<ReportNode type="Step">
<Data>
    <Name>"Login"- Smart Identification</Name>
    <Description>&lt;P&gt;&lt;span class="text"&gt;The smart identification mechanism was invoked.&lt;/span&gt;&lt;/P&gt;&lt;P&gt;&lt;SPAN class=text&gt;Reason: object not unique (2 objects found)&lt;/SPAN&gt;&lt;/P&gt;           &lt;SPAN class=text&gt;&lt;b&gt;Original description:&lt;/b&gt;&lt;/SPAN&gt;&lt;br&gt;micclass=Browser&lt;br&gt;&lt;P&gt;&lt;FONT face=Verdana size=2&gt;&lt;SPAN class=text&gt;&lt;B&gt;Smart Identification Alternative Description: &lt;/B&gt;&lt;/SPAN&gt;&lt;/FONT&gt;&lt;/P&gt;&lt;FONT face=Verdana size=2&gt;&lt;u&gt;Base filter properties (2 objects found)&amp;nbsp;&lt;/FONT&gt;&lt;/u&gt;&lt;br&gt;
micclass=Browser&lt;br&gt;&lt;br&gt;&lt;FONT face=Verdana size=2&gt;&lt;u&gt;Optional filter properties&lt;/FONT&gt;&lt;/u&gt;&lt;br&gt;
name=Oracle Applications Home Page&lt;SPAN class=Failed&gt; (Skipped)&lt;/SPAN&gt;&lt;br&gt;title=Oracle Applications Home Page&lt;SPAN class=Failed&gt; (Skipped)&lt;/SPAN&gt;&lt;br&gt;openurl=http://www.bing.com&lt;SPAN class=passed&gt; (Used&lt;/SPAN&gt;, 1 matches)&lt;/SPAN&gt;&lt;br&gt;opentitle=&lt;SPAN class=warning&gt; (Ignored)&lt;FONT color=#000000&gt;&lt;/FONT&gt;&lt;/SPAN&gt;&lt;br&gt;hasstatusbar=-1&lt;SPAN class=warning&gt; (Ignored)&lt;FONT color=#000000&gt;&lt;/FONT&gt;&lt;/SPAN&gt;&lt;br&gt;hasmenubar=-1&lt;SPAN class=warning&gt; (Ignored)&lt;FONT color=#000000&gt;&lt;/FONT&gt;&lt;/SPAN&gt;&lt;br&gt;hastoolbar=-1&lt;SPAN class=warning&gt; (Ignored)&lt;FONT color=#000000&gt;&lt;/FONT&gt;&lt;/SPAN&gt;&lt;br&gt;openedbytestingtool=0&lt;SPAN class=warning&gt; (Ignored)&lt;FONT color=#000000&gt;&lt;/FONT&gt;&lt;/SPAN&gt;&lt;br&gt;number of tabs=1&lt;SPAN class=warning&gt; (Ignored)&lt;FONT color=#000000&gt;&lt;/FONT&gt;&lt;/SPAN&gt;&lt;br&gt;</Description>
    <StartTime>2015-11-04 11:40:05</StartTime>
    <Result>Done</Result>
    <Extension>
      <TestObject>
        <Repository>C:\Users\sravanthi\Documents\GitHub\RACK-EBS-Master-Data\Business Components\Libraries\Object Repository\Oracle_EBS.tsr</Repository>
        <Path>
          <Object>
            <Type>Browser</Type>
            <Name><![CDATA[Login]]></Name>
          </Object>
        </Path>
        <OperationData><![CDATA[<P><span class="text">The smart identification mechanism was invoked.</span></P><P><SPAN class=text>Reason: object not unique (2 objects found)</SPAN></P>           <SPAN class=text><b>Original description:</b></SPAN><br>micclass=Browser<br><P><FONT face=Verdana size=2><SPAN class=text><B>Smart Identification Alternative Description: </B></SPAN></FONT></P><FONT face=Verdana size=2><u>Base filter properties (2 objects found)&nbsp;</FONT></u><br>
micclass=Browser<br><br><FONT face=Verdana size=2><u>Optional filter properties</FONT></u><br>
name=Oracle Applications Home Page<SPAN class=Failed> (Skipped)</SPAN><br>title=Oracle Applications Home Page<SPAN class=Failed> (Skipped)</SPAN><br>openurl=http://www.bing.com<SPAN class=passed> (Used</SPAN>, 1 matches)</SPAN><br>opentitle=<SPAN class=warning> (Ignored)<FONT color=#000000></FONT></SPAN><br>hasstatusbar=-1<SPAN class=warning> (Ignored)<FONT color=#000000></FONT></SPAN><br>hasmenubar=-1<SPAN class=warning> (Ignored)<FONT color=#000000></FONT></SPAN><br>hastoolbar=-1<SPAN class=warning> (Ignored)<FONT color=#000000></FONT></SPAN><br>openedbytestingtool=0<SPAN class=warning> (Ignored)<FONT color=#000000></FONT></SPAN><br>number of tabs=1<SPAN class=warning> (Ignored)<FONT color=#000000></FONT></SPAN><br>]]></OperationData>
      </TestObject>
      <IconKey>da8fe7478c1f409db486703ef05c28ae</IconKey>
    </Extension>
  </Data>
</ReportNode>
<ReportNode type="Step">
<Data>
    <Name>"Login"- Smart Identification</Name>
    <Description>&lt;P&gt;&lt;span class="text"&gt;The smart identification mechanism was invoked.&lt;/span&gt;&lt;/P&gt;&lt;P&gt;&lt;SPAN class=text&gt;Reason: object not unique (2 objects found)&lt;/SPAN&gt;&lt;/P&gt;           &lt;SPAN class=text&gt;&lt;b&gt;Original description:&lt;/b&gt;&lt;/SPAN&gt;&lt;br&gt;micclass=Browser&lt;br&gt;&lt;P&gt;&lt;FONT face=Verdana size=2&gt;&lt;SPAN class=text&gt;&lt;B&gt;Smart Identification Alternative Description: &lt;/B&gt;&lt;/SPAN&gt;&lt;/FONT&gt;&lt;/P&gt;&lt;FONT face=Verdana size=2&gt;&lt;u&gt;Base filter properties (2 objects found)&amp;nbsp;&lt;/FONT&gt;&lt;/u&gt;&lt;br&gt;
micclass=Browser&lt;br&gt;&lt;br&gt;&lt;FONT face=Verdana size=2&gt;&lt;u&gt;Optional filter properties&lt;/FONT&gt;&lt;/u&gt;&lt;br&gt;
name=Oracle Applications Home Page&lt;SPAN class=Failed&gt; (Skipped)&lt;/SPAN&gt;&lt;br&gt;title=Oracle Applications Home Page&lt;SPAN class=Failed&gt; (Skipped)&lt;/SPAN&gt;&lt;br&gt;openurl=http://www.bing.com&lt;SPAN class=passed&gt; (Used&lt;/SPAN&gt;, 1 matches)&lt;/SPAN&gt;&lt;br&gt;opentitle=&lt;SPAN class=warning&gt; (Ignored)&lt;FONT color=#000000&gt;&lt;/FONT&gt;&lt;/SPAN&gt;&lt;br&gt;hasstatusbar=-1&lt;SPAN class=warning&gt; (Ignored)&lt;FONT color=#000000&gt;&lt;/FONT&gt;&lt;/SPAN&gt;&lt;br&gt;hasmenubar=-1&lt;SPAN class=warning&gt; (Ignored)&lt;FONT color=#000000&gt;&lt;/FONT&gt;&lt;/SPAN&gt;&lt;br&gt;hastoolbar=-1&lt;SPAN class=warning&gt; (Ignored)&lt;FONT color=#000000&gt;&lt;/FONT&gt;&lt;/SPAN&gt;&lt;br&gt;openedbytestingtool=0&lt;SPAN class=warning&gt; (Ignored)&lt;FONT color=#000000&gt;&lt;/FONT&gt;&lt;/SPAN&gt;&lt;br&gt;number of tabs=1&lt;SPAN class=warning&gt; (Ignored)&lt;FONT color=#000000&gt;&lt;/FONT&gt;&lt;/SPAN&gt;&lt;br&gt;</Description>
    <StartTime>2015-11-04 11:40:05</StartTime>
    <Result>Done</Result>
    <Extension>
      <TestObject>
        <Repository>C:\Users\sravanthi\Documents\GitHub\RACK-EBS-Master-Data\Business Components\Libraries\Object Repository\Oracle_EBS.tsr</Repository>
        <Path>
          <Object>
            <Type>Browser</Type>
            <Name><![CDATA[Login]]></Name>
          </Object>
        </Path>
        <OperationData><![CDATA[<P><span class="text">The smart identification mechanism was invoked.</span></P><P><SPAN class=text>Reason: object not unique (2 objects found)</SPAN></P>           <SPAN class=text><b>Original description:</b></SPAN><br>micclass=Browser<br><P><FONT face=Verdana size=2><SPAN class=text><B>Smart Identification Alternative Description: </B></SPAN></FONT></P><FONT face=Verdana size=2><u>Base filter properties (2 objects found)&nbsp;</FONT></u><br>
micclass=Browser<br><br><FONT face=Verdana size=2><u>Optional filter properties</FONT></u><br>
name=Oracle Applications Home Page<SPAN class=Failed> (Skipped)</SPAN><br>title=Oracle Applications Home Page<SPAN class=Failed> (Skipped)</SPAN><br>openurl=http://www.bing.com<SPAN class=passed> (Used</SPAN>, 1 matches)</SPAN><br>opentitle=<SPAN class=warning> (Ignored)<FONT color=#000000></FONT></SPAN><br>hasstatusbar=-1<SPAN class=warning> (Ignored)<FONT color=#000000></FONT></SPAN><br>hasmenubar=-1<SPAN class=warning> (Ignored)<FONT color=#000000></FONT></SPAN><br>hastoolbar=-1<SPAN class=warning> (Ignored)<FONT color=#000000></FONT></SPAN><br>openedbytestingtool=0<SPAN class=warning> (Ignored)<FONT color=#000000></FONT></SPAN><br>number of tabs=1<SPAN class=warning> (Ignored)<FONT color=#000000></FONT></SPAN><br>]]></OperationData>
      </TestObject>
      <IconKey>da8fe7478c1f409db486703ef05c28ae</IconKey>
    </Extension>
  </Data>
</ReportNode>
<ReportNode type="Step">
<Data>
    <Name>"Login"- Smart Identification</Name>
    <Description>&lt;P&gt;&lt;span class="text"&gt;The smart identification mechanism was invoked.&lt;/span&gt;&lt;/P&gt;&lt;P&gt;&lt;SPAN class=text&gt;Reason: object not unique (2 objects found)&lt;/SPAN&gt;&lt;/P&gt;           &lt;SPAN class=text&gt;&lt;b&gt;Original description:&lt;/b&gt;&lt;/SPAN&gt;&lt;br&gt;micclass=Browser&lt;br&gt;&lt;P&gt;&lt;FONT face=Verdana size=2&gt;&lt;SPAN class=text&gt;&lt;B&gt;Smart Identification Alternative Description: &lt;/B&gt;&lt;/SPAN&gt;&lt;/FONT&gt;&lt;/P&gt;&lt;FONT face=Verdana size=2&gt;&lt;u&gt;Base filter properties (2 objects found)&amp;nbsp;&lt;/FONT&gt;&lt;/u&gt;&lt;br&gt;
micclass=Browser&lt;br&gt;&lt;br&gt;&lt;FONT face=Verdana size=2&gt;&lt;u&gt;Optional filter properties&lt;/FONT&gt;&lt;/u&gt;&lt;br&gt;
name=Oracle Applications Home Page&lt;SPAN class=Failed&gt; (Skipped)&lt;/SPAN&gt;&lt;br&gt;title=Oracle Applications Home Page&lt;SPAN class=Failed&gt; (Skipped)&lt;/SPAN&gt;&lt;br&gt;openurl=http://www.bing.com&lt;SPAN class=passed&gt; (Used&lt;/SPAN&gt;, 1 matches)&lt;/SPAN&gt;&lt;br&gt;opentitle=&lt;SPAN class=warning&gt; (Ignored)&lt;FONT color=#000000&gt;&lt;/FONT&gt;&lt;/SPAN&gt;&lt;br&gt;hasstatusbar=-1&lt;SPAN class=warning&gt; (Ignored)&lt;FONT color=#000000&gt;&lt;/FONT&gt;&lt;/SPAN&gt;&lt;br&gt;hasmenubar=-1&lt;SPAN class=warning&gt; (Ignored)&lt;FONT color=#000000&gt;&lt;/FONT&gt;&lt;/SPAN&gt;&lt;br&gt;hastoolbar=-1&lt;SPAN class=warning&gt; (Ignored)&lt;FONT color=#000000&gt;&lt;/FONT&gt;&lt;/SPAN&gt;&lt;br&gt;openedbytestingtool=0&lt;SPAN class=warning&gt; (Ignored)&lt;FONT color=#000000&gt;&lt;/FONT&gt;&lt;/SPAN&gt;&lt;br&gt;number of tabs=1&lt;SPAN class=warning&gt; (Ignored)&lt;FONT color=#000000&gt;&lt;/FONT&gt;&lt;/SPAN&gt;&lt;br&gt;</Description>
    <StartTime>2015-11-04 11:40:05</StartTime>
    <Result>Done</Result>
    <Extension>
      <TestObject>
        <Repository>C:\Users\sravanthi\Documents\GitHub\RACK-EBS-Master-Data\Business Components\Libraries\Object Repository\Oracle_EBS.tsr</Repository>
        <Path>
          <Object>
            <Type>Browser</Type>
            <Name><![CDATA[Login]]></Name>
          </Object>
        </Path>
        <OperationData><![CDATA[<P><span class="text">The smart identification mechanism was invoked.</span></P><P><SPAN class=text>Reason: object not unique (2 objects found)</SPAN></P>           <SPAN class=text><b>Original description:</b></SPAN><br>micclass=Browser<br><P><FONT face=Verdana size=2><SPAN class=text><B>Smart Identification Alternative Description: </B></SPAN></FONT></P><FONT face=Verdana size=2><u>Base filter properties (2 objects found)&nbsp;</FONT></u><br>
micclass=Browser<br><br><FONT face=Verdana size=2><u>Optional filter properties</FONT></u><br>
name=Oracle Applications Home Page<SPAN class=Failed> (Skipped)</SPAN><br>title=Oracle Applications Home Page<SPAN class=Failed> (Skipped)</SPAN><br>openurl=http://www.bing.com<SPAN class=passed> (Used</SPAN>, 1 matches)</SPAN><br>opentitle=<SPAN class=warning> (Ignored)<FONT color=#000000></FONT></SPAN><br>hasstatusbar=-1<SPAN class=warning> (Ignored)<FONT color=#000000></FONT></SPAN><br>hasmenubar=-1<SPAN class=warning> (Ignored)<FONT color=#000000></FONT></SPAN><br>hastoolbar=-1<SPAN class=warning> (Ignored)<FONT color=#000000></FONT></SPAN><br>openedbytestingtool=0<SPAN class=warning> (Ignored)<FONT color=#000000></FONT></SPAN><br>number of tabs=1<SPAN class=warning> (Ignored)<FONT color=#000000></FONT></SPAN><br>]]></OperationData>
      </TestObject>
      <IconKey>da8fe7478c1f409db486703ef05c28ae</IconKey>
    </Extension>
  </Data>
</ReportNode>
<ReportNode type="Step">
<Data>
    <Name>"Login"- Smart Identification</Name>
    <Description>&lt;P&gt;&lt;span class="text"&gt;The smart identification mechanism was invoked.&lt;/span&gt;&lt;/P&gt;&lt;P&gt;&lt;SPAN class=text&gt;Reason: object not unique (2 objects found)&lt;/SPAN&gt;&lt;/P&gt;           &lt;SPAN class=text&gt;&lt;b&gt;Original description:&lt;/b&gt;&lt;/SPAN&gt;&lt;br&gt;micclass=Browser&lt;br&gt;&lt;P&gt;&lt;FONT face=Verdana size=2&gt;&lt;SPAN class=text&gt;&lt;B&gt;Smart Identification Alternative Description: &lt;/B&gt;&lt;/SPAN&gt;&lt;/FONT&gt;&lt;/P&gt;&lt;FONT face=Verdana size=2&gt;&lt;u&gt;Base filter properties (2 objects found)&amp;nbsp;&lt;/FONT&gt;&lt;/u&gt;&lt;br&gt;
micclass=Browser&lt;br&gt;&lt;br&gt;&lt;FONT face=Verdana size=2&gt;&lt;u&gt;Optional filter properties&lt;/FONT&gt;&lt;/u&gt;&lt;br&gt;
name=Oracle Applications Home Page&lt;SPAN class=Failed&gt; (Skipped)&lt;/SPAN&gt;&lt;br&gt;title=Oracle Applications Home Page&lt;SPAN class=Failed&gt; (Skipped)&lt;/SPAN&gt;&lt;br&gt;openurl=http://www.bing.com&lt;SPAN class=passed&gt; (Used&lt;/SPAN&gt;, 1 matches)&lt;/SPAN&gt;&lt;br&gt;opentitle=&lt;SPAN class=warning&gt; (Ignored)&lt;FONT color=#000000&gt;&lt;/FONT&gt;&lt;/SPAN&gt;&lt;br&gt;hasstatusbar=-1&lt;SPAN class=warning&gt; (Ignored)&lt;FONT color=#000000&gt;&lt;/FONT&gt;&lt;/SPAN&gt;&lt;br&gt;hasmenubar=-1&lt;SPAN class=warning&gt; (Ignored)&lt;FONT color=#000000&gt;&lt;/FONT&gt;&lt;/SPAN&gt;&lt;br&gt;hastoolbar=-1&lt;SPAN class=warning&gt; (Ignored)&lt;FONT color=#000000&gt;&lt;/FONT&gt;&lt;/SPAN&gt;&lt;br&gt;openedbytestingtool=0&lt;SPAN class=warning&gt; (Ignored)&lt;FONT color=#000000&gt;&lt;/FONT&gt;&lt;/SPAN&gt;&lt;br&gt;number of tabs=1&lt;SPAN class=warning&gt; (Ignored)&lt;FONT color=#000000&gt;&lt;/FONT&gt;&lt;/SPAN&gt;&lt;br&gt;</Description>
    <StartTime>2015-11-04 11:40:05</StartTime>
    <Result>Done</Result>
    <Extension>
      <TestObject>
        <Repository>C:\Users\sravanthi\Documents\GitHub\RACK-EBS-Master-Data\Business Components\Libraries\Object Repository\Oracle_EBS.tsr</Repository>
        <Path>
          <Object>
            <Type>Browser</Type>
            <Name><![CDATA[Login]]></Name>
          </Object>
        </Path>
        <OperationData><![CDATA[<P><span class="text">The smart identification mechanism was invoked.</span></P><P><SPAN class=text>Reason: object not unique (2 objects found)</SPAN></P>           <SPAN class=text><b>Original description:</b></SPAN><br>micclass=Browser<br><P><FONT face=Verdana size=2><SPAN class=text><B>Smart Identification Alternative Description: </B></SPAN></FONT></P><FONT face=Verdana size=2><u>Base filter properties (2 objects found)&nbsp;</FONT></u><br>
micclass=Browser<br><br><FONT face=Verdana size=2><u>Optional filter properties</FONT></u><br>
name=Oracle Applications Home Page<SPAN class=Failed> (Skipped)</SPAN><br>title=Oracle Applications Home Page<SPAN class=Failed> (Skipped)</SPAN><br>openurl=http://www.bing.com<SPAN class=passed> (Used</SPAN>, 1 matches)</SPAN><br>opentitle=<SPAN class=warning> (Ignored)<FONT color=#000000></FONT></SPAN><br>hasstatusbar=-1<SPAN class=warning> (Ignored)<FONT color=#000000></FONT></SPAN><br>hasmenubar=-1<SPAN class=warning> (Ignored)<FONT color=#000000></FONT></SPAN><br>hastoolbar=-1<SPAN class=warning> (Ignored)<FONT color=#000000></FONT></SPAN><br>openedbytestingtool=0<SPAN class=warning> (Ignored)<FONT color=#000000></FONT></SPAN><br>number of tabs=1<SPAN class=warning> (Ignored)<FONT color=#000000></FONT></SPAN><br>]]></OperationData>
      </TestObject>
      <IconKey>da8fe7478c1f409db486703ef05c28ae</IconKey>
    </Extension>
  </Data>
</ReportNode>
<ReportNode type="Step">
